activecampaign/__init__.py
activecampaign/apps.py
activecampaign/tests.py
activecampaign/views.py
activecampaign/admin/__init__.py
activecampaign/admin/campaign.py
activecampaign/admin/list.py
activecampaign/admin/message.py
activecampaign/migrations/0001_initial.py
activecampaign/migrations/__init__.py
activecampaign/models/__init__.py
activecampaign/models/account_view.py
activecampaign/models/activecampaign.py
activecampaign/models/address.py
activecampaign/models/automation.py
activecampaign/models/branding.py
activecampaign/models/campaign.py
activecampaign/models/contact.py
activecampaign/models/deal.py
activecampaign/models/event_tracking.py
activecampaign/models/form.py
activecampaign/models/group.py
activecampaign/models/list.py
activecampaign/models/message.py
activecampaign/models/organization.py
activecampaign/models/segment.py
activecampaign/models/settings.py
activecampaign/models/singlesignon.py
activecampaign/models/site_tracking.py
activecampaign/models/tags.py
activecampaign/models/tasks.py
activecampaign/models/user.py
activecampaign/models/webhook.py
django_activecampaign-0.1.2.dist-info/DESCRIPTION.rst
django_activecampaign-0.1.2.dist-info/METADATA
django_activecampaign-0.1.2.dist-info/RECORD
django_activecampaign-0.1.2.dist-info/WHEEL
django_activecampaign-0.1.2.dist-info/metadata.json
django_activecampaign-0.1.2.dist-info/top_level.txt
